traffic_light_controller.v
`timescale 1ns / 1ps

module traffic_light_controller #(
    parameter CLK_FREQ = 100_000_000, // 100 MHz System Clock
    parameter GREEN_TIME = 30,        // 30 Seconds Green Light
    parameter YELLOW_TIME = 3         // 3 Seconds Yellow Light
)(
    input  wire clk,
    input  wire rst,
    
    // Road 1
    output reg YESIL1,
    output reg SARI1,
    output reg KIRMIZI1,
    
    // Road 2
    output reg YESIL2,
    output reg SARI2,
    output reg KIRMIZI2,
    
    // Road 3
    output reg YESIL3,
    output reg SARI3,
    output reg KIRMIZI3,
    
    // Road 4
    output reg YESIL4,
    output reg SARI4,
    output reg KIRMIZI4,
    
    // Right Turn Indicators (Blinking)
    output wire SAG_OUT_1,
    output wire SAG_OUT_2,
    output wire SAG_OUT_3,
    output wire SAG_OUT_4
);

    // =========================================================================
    // Local Parameters & State Definitions
    // =========================================================================
    
    // FSM States
    localparam [2:0] 
        S_R1_G = 3'd0,
        S_R1_Y = 3'd1,
        S_R2_G = 3'd2,
        S_R2_Y = 3'd3,
        S_R3_G = 3'd4,
        S_R3_Y = 3'd5,
        S_R4_G = 3'd6,
        S_R4_Y = 3'd7;

    // Timer Thresholds to convert seconds to clock cycles
    // Note: If using this for simulation with small cycle counts, ensure params are set appropriately.
    localparam [31:0] GREEN_CYCLES  = GREEN_TIME * CLK_FREQ;
    localparam [31:0] YELLOW_CYCLES = YELLOW_TIME * CLK_FREQ;
    
    // 0.5s for blinking (1Hz total period: 0.5s ON, 0.5s OFF)
    localparam [31:0] BLINK_HALF_PERIOD = CLK_FREQ / 2; 

    // =========================================================================
    // Internal Registers
    // =========================================================================
    
    reg [2:0]   current_state, next_state;
    reg [31:0]  timer_counter;
    reg         timer_reset;
    
    // Blinking logic registers
    reg [31:0]  blink_counter;
    reg         blink_state; // 1 = ON, 0 = OFF

    // =========================================================================
    // Right Turn Blinking Logic (Independent 1Hz)
    // =========================================================================
    
    always @(posedge clk or posedge rst) begin
        if (rst) begin
            blink_counter <= 0;
            blink_state   <= 0;
        end else begin
            if (blink_counter >= BLINK_HALF_PERIOD - 1) begin
                blink_counter <= 0;
                blink_state   <= ~blink_state; // Toggle state every 0.5s
            end else begin
                blink_counter <= blink_counter + 1;
            end
        end
    end

    // Assign blinking state to outputs
    assign SAG_OUT_1 = blink_state;
    assign SAG_OUT_2 = blink_state;
    assign SAG_OUT_3 = blink_state;
    assign SAG_OUT_4 = blink_state;

    // =========================================================================
    // Traffic Light FSM System
    // =========================================================================

    // State Register
    always @(posedge clk or posedge rst) begin
        if (rst) begin
            current_state <= S_R1_G;
            timer_counter <= 0;
        end else begin
            if (timer_reset) begin
                current_state <= next_state;
                timer_counter <= 0;
            end else begin
                timer_counter <= timer_counter + 1;
            end
        end
    end

    // Next State Logic
    always @(*) begin
        // Default assignments to prevent latches
        next_state  = current_state;
        timer_reset = 0;
        
        case (current_state)
            S_R1_G: begin
                // Road 1 Green for GREEN_TIME
                if (timer_counter >= GREEN_CYCLES - 1) begin
                    next_state  = S_R1_Y;
                    timer_reset = 1;
                end
            end
            
            S_R1_Y: begin
                // Road 1 Yellow for YELLOW_TIME
                if (timer_counter >= YELLOW_CYCLES - 1) begin
                    next_state  = S_R2_G;
                    timer_reset = 1;
                end
            end
            
            S_R2_G: begin
                // Road 2 Green
                if (timer_counter >= GREEN_CYCLES - 1) begin
                    next_state  = S_R2_Y;
                    timer_reset = 1;
                end
            end
            
            S_R2_Y: begin
                // Road 2 Yellow
                if (timer_counter >= YELLOW_CYCLES - 1) begin
                    next_state  = S_R3_G;
                    timer_reset = 1;
                end
            end
            
            S_R3_G: begin
                // Road 3 Green
                if (timer_counter >= GREEN_CYCLES - 1) begin
                    next_state  = S_R3_Y;
                    timer_reset = 1;
                end
            end
            
            S_R3_Y: begin
                // Road 3 Yellow
                if (timer_counter >= YELLOW_CYCLES - 1) begin
                    next_state  = S_R4_G;
                    timer_reset = 1;
                end
            end
            
            S_R4_G: begin
                // Road 4 Green
                if (timer_counter >= GREEN_CYCLES - 1) begin
                    next_state  = S_R4_Y;
                    timer_reset = 1;
                end
            end
            
            S_R4_Y: begin
                // Road 4 Yellow -> Loop back to Road 1 Green
                if (timer_counter >= YELLOW_CYCLES - 1) begin
                    next_state  = S_R1_G;
                    timer_reset = 1;
                end
            end
            
            default: begin
                next_state  = S_R1_G;
                timer_reset = 1;
            end
        endcase
    end

    // Output Logic
    // Default all to RED, then override based on state
    always @(*) begin
        // Default: All Red
        YESIL1 = 0; SARI1 = 0; KIRMIZI1 = 1;
        YESIL2 = 0; SARI2 = 0; KIRMIZI2 = 1;
        YESIL3 = 0; SARI3 = 0; KIRMIZI3 = 1;
        YESIL4 = 0; SARI4 = 0; KIRMIZI4 = 1;
        
case (current_state)

    S_R1_G: begin
        YESIL1 = 1; KIRMIZI1 = 0;
    end

    S_R1_Y: begin
        // Y1 + Y2
        SARI1 = 1; KIRMIZI1 = 0;
        SARI2 = 1; KIRMIZI2 = 0;
    end

    S_R2_G: begin
        YESIL2 = 1; KIRMIZI2 = 0;
    end

    S_R2_Y: begin
        // Y2 + Y3
        SARI2 = 1; KIRMIZI2 = 0;
        SARI3 = 1; KIRMIZI3 = 0;
    end

    S_R3_G: begin
        YESIL3 = 1; KIRMIZI3 = 0;
    end

    S_R3_Y: begin
        // Y3 + Y4
        SARI3 = 1; KIRMIZI3 = 0;
        SARI4 = 1; KIRMIZI4 = 0;
    end

    S_R4_G: begin
        YESIL4 = 1; KIRMIZI4 = 0;
    end

    S_R4_Y: begin
        // Y4 + Y1
        SARI4 = 1; KIRMIZI4 = 0;
        SARI1 = 1; KIRMIZI1 = 0;
    end

endcase

    end

endmodule

tb_traffic_light_controller.v
`timescale 1ns / 1ps

module tb_traffic_light_controller;

    // =========================================================================
    // Signal Declarations
    // =========================================================================
    reg clk;
    reg rst;
    
    wire YESIL1, SARI1, KIRMIZI1;
    wire YESIL2, SARI2, KIRMIZI2;
    wire YESIL3, SARI3, KIRMIZI3;
    wire YESIL4, SARI4, KIRMIZI4;
    wire SAG_OUT_1, SAG_OUT_2, SAG_OUT_3, SAG_OUT_4;

    // =========================================================================
    // Clock Generation (100MHz -> 10ns period)
    // =========================================================================
    initial begin
        clk = 0;
        forever #5 clk = ~clk;
    end

    // =========================================================================
    // DUT Instantiation
    // =========================================================================
    traffic_light_controller #(
        .CLK_FREQ(4),
        .GREEN_TIME(10),
        .YELLOW_TIME(2)
    ) dut (
        .clk(clk),
        .rst(rst),
        .YESIL1(YESIL1), .SARI1(SARI1), .KIRMIZI1(KIRMIZI1),
        .YESIL2(YESIL2), .SARI2(SARI2), .KIRMIZI2(KIRMIZI2),
        .YESIL3(YESIL3), .SARI3(SARI3), .KIRMIZI3(KIRMIZI3),
        .YESIL4(YESIL4), .SARI4(SARI4), .KIRMIZI4(KIRMIZI4),
        .SAG_OUT_1(SAG_OUT_1),
        .SAG_OUT_2(SAG_OUT_2),
        .SAG_OUT_3(SAG_OUT_3),
        .SAG_OUT_4(SAG_OUT_4)
    );

    // =========================================================================
    // Test Stimulus
    // =========================================================================
    initial begin
        $dumpfile("dalga.vcd");
        $dumpvars(0, tb_traffic_light_controller); // <<< KRİTİK SATIR

        rst = 1;
        #100;
        rst = 0;

        #3000;
        $display("Simulation Completed.");
        $finish;
    end

endmodule

dalga.vcd
$date
	Mon Jan 19 14:39:27 2026
$end
$version
	Icarus Verilog
$end
$timescale
	1ps
$end
$scope module tb_traffic_light_controller $end
$var wire 1 ! YESIL4 $end
$var wire 1 " YESIL3 $end
$var wire 1 # YESIL2 $end
$var wire 1 $ YESIL1 $end
$var wire 1 % SARI4 $end
$var wire 1 & SARI3 $end
$var wire 1 ' SARI2 $end
$var wire 1 ( SARI1 $end
$var wire 1 ) SAG_OUT_4 $end
$var wire 1 * SAG_OUT_3 $end
$var wire 1 + SAG_OUT_2 $end
$var wire 1 , SAG_OUT_1 $end
$var wire 1 - KIRMIZI4 $end
$var wire 1 . KIRMIZI3 $end
$var wire 1 / KIRMIZI2 $end
$var wire 1 0 KIRMIZI1 $end
$var reg 1 1 clk $end
$var reg 1 2 rst $end
$scope module dut $end
$var wire 1 , SAG_OUT_1 $end
$var wire 1 + SAG_OUT_2 $end
$var wire 1 * SAG_OUT_3 $end
$var wire 1 ) SAG_OUT_4 $end
$var wire 1 1 clk $end
$var wire 1 2 rst $end
$var parameter 32 3 BLINK_HALF_PERIOD $end
$var parameter 32 4 CLK_FREQ $end
$var parameter 32 5 GREEN_CYCLES $end
$var parameter 32 6 GREEN_TIME $end
$var parameter 3 7 S_R1_G $end
$var parameter 3 8 S_R1_Y $end
$var parameter 3 9 S_R2_G $end
$var parameter 3 : S_R2_Y $end
$var parameter 3 ; S_R3_G $end
$var parameter 3 < S_R3_Y $end
$var parameter 3 = S_R4_G $end
$var parameter 3 > S_R4_Y $end
$var parameter 32 ? YELLOW_CYCLES $end
$var parameter 32 @ YELLOW_TIME $end
$var reg 1 0 KIRMIZI1 $end
$var reg 1 / KIRMIZI2 $end
$var reg 1 . KIRMIZI3 $end
$var reg 1 - KIRMIZI4 $end
$var reg 1 ( SARI1 $end
$var reg 1 ' SARI2 $end
$var reg 1 & SARI3 $end
$var reg 1 % SARI4 $end
$var reg 1 $ YESIL1 $end
$var reg 1 # YESIL2 $end
$var reg 1 " YESIL3 $end
$var reg 1 ! YESIL4 $end
$var reg 32 A blink_counter [31:0] $end
$var reg 1 B blink_state $end
$var reg 3 C current_state [2:0] $end
$var reg 3 D next_state [2:0] $end
$var reg 32 E timer_counter [31:0] $end
$var reg 1 F timer_reset $end
$upscope $end
$upscope $end
$enddefinitions $end
$comment Show the parameter values. $end
$dumpall
b10 @
b1000 ?
b111 >
b110 =
b101 <
b100 ;
b11 :
b10 9
b1 8
b0 7
b1010 6
b101000 5
b100 4
b10 3
$end
#0
$dumpvars
0F
b0 E
b0 D
b0 C
0B
b0 A
12
01
00
1/
1.
1-
0,
0+
0*
0)
0(
0'
0&
0%
1$
0#
0"
0!
$end
#5000
11
#10000
01
#15000
11
#20000
01
#25000
11
#30000
01
#35000
11
#40000
01
#45000
11
#50000
01
#55000
11
#60000
01
#65000
11
#70000
01
#75000
11
#80000
01
#85000
11
#90000
01
#95000
11
#100000
01
02
#105000
b1 E
b1 A
11
#110000
01
#115000
1)
1*
1+
1,
1B
b0 A
b10 E
11
#120000
01
#125000
b11 E
b1 A
11
#130000
01
#135000
0)
0*
0+
0,
0B
b0 A
b100 E
11
#140000
01
#145000
b101 E
b1 A
11
#150000
01
#155000
1)
1*
1+
1,
1B
b0 A
b110 E
11
#160000
01
#165000
b111 E
b1 A
11
#170000
01
#175000
0)
0*
0+
0,
0B
b0 A
b1000 E
11
#180000
01
#185000
b1001 E
b1 A
11
#190000
01
#195000
1)
1*
1+
1,
1B
b0 A
b1010 E
11
#200000
01
#205000
b1011 E
b1 A
11
#210000
01
#215000
0)
0*
0+
0,
0B
b0 A
b1100 E
11
#220000
01
#225000
b1101 E
b1 A
11
#230000
01
#235000
1)
1*
1+
1,
1B
b0 A
b1110 E
11
#240000
01
#245000
b1111 E
b1 A
11
#250000
01
#255000
0)
0*
0+
0,
0B
b0 A
b10000 E
11
#260000
01
#265000
b10001 E
b1 A
11
#270000
01
#275000
1)
1*
1+
1,
1B
b0 A
b10010 E
11
#280000
01
#285000
b10011 E
b1 A
11
#290000
01
#295000
0)
0*
0+
0,
0B
b0 A
b10100 E
11
#300000
01
#305000
b10101 E
b1 A
11
#310000
01
#315000
1)
1*
1+
1,
1B
b0 A
b10110 E
11
#320000
01
#325000
b10111 E
b1 A
11
#330000
01
#335000
0)
0*
0+
0,
0B
b0 A
b11000 E
11
#340000
01
#345000
b11001 E
b1 A
11
#350000
01
#355000
1)
1*
1+
1,
1B
b0 A
b11010 E
11
#360000
01
#365000
b11011 E
b1 A
11
#370000
01
#375000
0)
0*
0+
0,
0B
b0 A
b11100 E
11
#380000
01
#385000
b11101 E
b1 A
11
#390000
01
#395000
1)
1*
1+
1,
1B
b0 A
b11110 E
11
#400000
01
#405000
b11111 E
b1 A
11
#410000
01
#415000
0)
0*
0+
0,
0B
b0 A
b100000 E
11
#420000
01
#425000
b100001 E
b1 A
11
#430000
01
#435000
1)
1*
1+
1,
1B
b0 A
b100010 E
11
#440000
01
#445000
b100011 E
b1 A
11
#450000
01
#455000
0)
0*
0+
0,
0B
b0 A
b100100 E
11
#460000
01
#465000
b100101 E
b1 A
11
#470000
01
#475000
1)
1*
1+
1,
1B
b0 A
b100110 E
11
#480000
01
#485000
1F
b1 D
b100111 E
b1 A
11
#490000
01
#495000
0/
1'
1(
00
0$
0F
0)
0*
0+
0,
0B
b0 A
b0 E
b1 C
11
#500000
01
#505000
b1 E
b1 A
11
#510000
01
#515000
1)
1*
1+
1,
1B
b0 A
b10 E
11
#520000
01
#525000
b11 E
b1 A
11
#530000
01
#535000
0)
0*
0+
0,
0B
b0 A
b100 E
11
#540000
01
#545000
b101 E
b1 A
11
#550000
01
#555000
1)
1*
1+
1,
1B
b0 A
b110 E
11
#560000
01
#565000
1F
b10 D
b111 E
b1 A
11
#570000
01
#575000
1#
0/
0'
10
0(
0F
0)
0*
0+
0,
0B
b0 A
b0 E
b10 C
11
#580000
01
#585000
b1 E
b1 A
11
#590000
01
#595000
1)
1*
1+
1,
1B
b0 A
b10 E
11
#600000
01
#605000
b11 E
b1 A
11
#610000
01
#615000
0)
0*
0+
0,
0B
b0 A
b100 E
11
#620000
01
#625000
b101 E
b1 A
11
#630000
01
#635000
1)
1*
1+
1,
1B
b0 A
b110 E
11
#640000
01
#645000
b111 E
b1 A
11
#650000
01
#655000
0)
0*
0+
0,
0B
b0 A
b1000 E
11
#660000
01
#665000
b1001 E
b1 A
11
#670000
01
#675000
1)
1*
1+
1,
1B
b0 A
b1010 E
11
#680000
01
#685000
b1011 E
b1 A
11
#690000
01
#695000
0)
0*
0+
0,
0B
b0 A
b1100 E
11
#700000
01
#705000
b1101 E
b1 A
11
#710000
01
#715000
1)
1*
1+
1,
1B
b0 A
b1110 E
11
#720000
01
#725000
b1111 E
b1 A
11
#730000
01
#735000
0)
0*
0+
0,
0B
b0 A
b10000 E
11
#740000
01
#745000
b10001 E
b1 A
11
#750000
01
#755000
1)
1*
1+
1,
1B
b0 A
b10010 E
11
#760000
01
#765000
b10011 E
b1 A
11
#770000
01
#775000
0)
0*
0+
0,
0B
b0 A
b10100 E
11
#780000
01
#785000
b10101 E
b1 A
11
#790000
01
#795000
1)
1*
1+
1,
1B
b0 A
b10110 E
11
#800000
01
#805000
b10111 E
b1 A
11
#810000
01
#815000
0)
0*
0+
0,
0B
b0 A
b11000 E
11
#820000
01
#825000
b11001 E
b1 A
11
#830000
01
#835000
1)
1*
1+
1,
1B
b0 A
b11010 E
11
#840000
01
#845000
b11011 E
b1 A
11
#850000
01
#855000
0)
0*
0+
0,
0B
b0 A
b11100 E
11
#860000
01
#865000
b11101 E
b1 A
11
#870000
01
#875000
1)
1*
1+
1,
1B
b0 A
b11110 E
11
#880000
01
#885000
b11111 E
b1 A
11
#890000
01
#895000
0)
0*
0+
0,
0B
b0 A
b100000 E
11
#900000
01
#905000
b100001 E
b1 A
11
#910000
01
#915000
1)
1*
1+
1,
1B
b0 A
b100010 E
11
#920000
01
#925000
b100011 E
b1 A
11
#930000
01
#935000
0)
0*
0+
0,
0B
b0 A
b100100 E
11
#940000
01
#945000
b100101 E
b1 A
11
#950000
01
#955000
1)
1*
1+
1,
1B
b0 A
b100110 E
11
#960000
01
#965000
1F
b11 D
b100111 E
b1 A
11
#970000
01
#975000
0.
1&
1'
0/
0#
0F
0)
0*
0+
0,
0B
b0 A
b0 E
b11 C
11
#980000
01
#985000
b1 E
b1 A
11
#990000
01
#995000
1)
1*
1+
1,
1B
b0 A
b10 E
11
#1000000
01
#1005000
b11 E
b1 A
11
#1010000
01
#1015000
0)
0*
0+
0,
0B
b0 A
b100 E
11
#1020000
01
#1025000
b101 E
b1 A
11
#1030000
01
#1035000
1)
1*
1+
1,
1B
b0 A
b110 E
11
#1040000
01
#1045000
1F
b100 D
b111 E
b1 A
11
#1050000
01
#1055000
1"
0.
0&
1/
0'
0F
0)
0*
0+
0,
0B
b0 A
b0 E
b100 C
11
#1060000
01
#1065000
b1 E
b1 A
11
#1070000
01
#1075000
1)
1*
1+
1,
1B
b0 A
b10 E
11
#1080000
01
#1085000
b11 E
b1 A
11
#1090000
01
#1095000
0)
0*
0+
0,
0B
b0 A
b100 E
11
#1100000
01
#1105000
b101 E
b1 A
11
#1110000
01
#1115000
1)
1*
1+
1,
1B
b0 A
b110 E
11
#1120000
01
#1125000
b111 E
b1 A
11
#1130000
01
#1135000
0)
0*
0+
0,
0B
b0 A
b1000 E
11
#1140000
01
#1145000
b1001 E
b1 A
11
#1150000
01
#1155000
1)
1*
1+
1,
1B
b0 A
b1010 E
11
#1160000
01
#1165000
b1011 E
b1 A
11
#1170000
01
#1175000
0)
0*
0+
0,
0B
b0 A
b1100 E
11
#1180000
01
#1185000
b1101 E
b1 A
11
#1190000
01
#1195000
1)
1*
1+
1,
1B
b0 A
b1110 E
11
#1200000
01
#1205000
b1111 E
b1 A
11
#1210000
01
#1215000
0)
0*
0+
0,
0B
b0 A
b10000 E
11
#1220000
01
#1225000
b10001 E
b1 A
11
#1230000
01
#1235000
1)
1*
1+
1,
1B
b0 A
b10010 E
11
#1240000
01
#1245000
b10011 E
b1 A
11
#1250000
01
#1255000
0)
0*
0+
0,
0B
b0 A
b10100 E
11
#1260000
01
#1265000
b10101 E
b1 A
11
#1270000
01
#1275000
1)
1*
1+
1,
1B
b0 A
b10110 E
11
#1280000
01
#1285000
b10111 E
b1 A
11
#1290000
01
#1295000
0)
0*
0+
0,
0B
b0 A
b11000 E
11
#1300000
01
#1305000
b11001 E
b1 A
11
#1310000
01
#1315000
1)
1*
1+
1,
1B
b0 A
b11010 E
11
#1320000
01
#1325000
b11011 E
b1 A
11
#1330000
01
#1335000
0)
0*
0+
0,
0B
b0 A
b11100 E
11
#1340000
01
#1345000
b11101 E
b1 A
11
#1350000
01
#1355000
1)
1*
1+
1,
1B
b0 A
b11110 E
11
#1360000
01
#1365000
b11111 E
b1 A
11
#1370000
01
#1375000
0)
0*
0+
0,
0B
b0 A
b100000 E
11
#1380000
01
#1385000
b100001 E
b1 A
11
#1390000
01
#1395000
1)
1*
1+
1,
1B
b0 A
b100010 E
11
#1400000
01
#1405000
b100011 E
b1 A
11
#1410000
01
#1415000
0)
0*
0+
0,
0B
b0 A
b100100 E
11
#1420000
01
#1425000
b100101 E
b1 A
11
#1430000
01
#1435000
1)
1*
1+
1,
1B
b0 A
b100110 E
11
#1440000
01
#1445000
1F
b101 D
b100111 E
b1 A
11
#1450000
01
#1455000
0-
1%
1&
0.
0"
0F
0)
0*
0+
0,
0B
b0 A
b0 E
b101 C
11
#1460000
01
#1465000
b1 E
b1 A
11
#1470000
01
#1475000
1)
1*
1+
1,
1B
b0 A
b10 E
11
#1480000
01
#1485000
b11 E
b1 A
11
#1490000
01
#1495000
0)
0*
0+
0,
0B
b0 A
b100 E
11
#1500000
01
#1505000
b101 E
b1 A
11
#1510000
01
#1515000
1)
1*
1+
1,
1B
b0 A
b110 E
11
#1520000
01
#1525000
1F
b110 D
b111 E
b1 A
11
#1530000
01
#1535000
1!
0-
0%
1.
0&
0F
0)
0*
0+
0,
0B
b0 A
b0 E
b110 C
11
#1540000
01
#1545000
b1 E
b1 A
11
#1550000
01
#1555000
1)
1*
1+
1,
1B
b0 A
b10 E
11
#1560000
01
#1565000
b11 E
b1 A
11
#1570000
01
#1575000
0)
0*
0+
0,
0B
b0 A
b100 E
11
#1580000
01
#1585000
b101 E
b1 A
11
#1590000
01
#1595000
1)
1*
1+
1,
1B
b0 A
b110 E
11
#1600000
01
#1605000
b111 E
b1 A
11
#1610000
01
#1615000
0)
0*
0+
0,
0B
b0 A
b1000 E
11
#1620000
01
#1625000
b1001 E
b1 A
11
#1630000
01
#1635000
1)
1*
1+
1,
1B
b0 A
b1010 E
11
#1640000
01
#1645000
b1011 E
b1 A
11
#1650000
01
#1655000
0)
0*
0+
0,
0B
b0 A
b1100 E
11
#1660000
01
#1665000
b1101 E
b1 A
11
#1670000
01
#1675000
1)
1*
1+
1,
1B
b0 A
b1110 E
11
#1680000
01
#1685000
b1111 E
b1 A
11
#1690000
01
#1695000
0)
0*
0+
0,
0B
b0 A
b10000 E
11
#1700000
01
#1705000
b10001 E
b1 A
11
#1710000
01
#1715000
1)
1*
1+
1,
1B
b0 A
b10010 E
11
#1720000
01
#1725000
b10011 E
b1 A
11
#1730000
01
#1735000
0)
0*
0+
0,
0B
b0 A
b10100 E
11
#1740000
01
#1745000
b10101 E
b1 A
11
#1750000
01
#1755000
1)
1*
1+
1,
1B
b0 A
b10110 E
11
#1760000
01
#1765000
b10111 E
b1 A
11
#1770000
01
#1775000
0)
0*
0+
0,
0B
b0 A
b11000 E
11
#1780000
01
#1785000
b11001 E
b1 A
11
#1790000
01
#1795000
1)
1*
1+
1,
1B
b0 A
b11010 E
11
#1800000
01
#1805000
b11011 E
b1 A
11
#1810000
01
#1815000
0)
0*
0+
0,
0B
b0 A
b11100 E
11
#1820000
01
#1825000
b11101 E
b1 A
11
#1830000
01
#1835000
1)
1*
1+
1,
1B
b0 A
b11110 E
11
#1840000
01
#1845000
b11111 E
b1 A
11
#1850000
01
#1855000
0)
0*
0+
0,
0B
b0 A
b100000 E
11
#1860000
01
#1865000
b100001 E
b1 A
11
#1870000
01
#1875000
1)
1*
1+
1,
1B
b0 A
b100010 E
11
#1880000
01
#1885000
b100011 E
b1 A
11
#1890000
01
#1895000
0)
0*
0+
0,
0B
b0 A
b100100 E
11
#1900000
01
#1905000
b100101 E
b1 A
11
#1910000
01
#1915000
1)
1*
1+
1,
1B
b0 A
b100110 E
11
#1920000
01
#1925000
1F
b111 D
b100111 E
b1 A
11
#1930000
01
#1935000
00
1(
1%
0-
0!
0F
0)
0*
0+
0,
0B
b0 A
b0 E
b111 C
11
#1940000
01
#1945000
b1 E
b1 A
11
#1950000
01
#1955000
1)
1*
1+
1,
1B
b0 A
b10 E
11
#1960000
01
#1965000
b11 E
b1 A
11
#1970000
01
#1975000
0)
0*
0+
0,
0B
b0 A
b100 E
11
#1980000
01
#1985000
b101 E
b1 A
11
#1990000
01
#1995000
1)
1*
1+
1,
1B
b0 A
b110 E
11
#2000000
01
#2005000
1F
b0 D
b111 E
b1 A
11
#2010000
01
#2015000
1$
1-
0%
00
0(
0F
0)
0*
0+
0,
0B
b0 A
b0 E
b0 C
11
#2020000
01
#2025000
b1 E
b1 A
11
#2030000
01
#2035000
1)
1*
1+
1,
1B
b0 A
b10 E
11
#2040000
01
#2045000
b11 E
b1 A
11
#2050000
01
#2055000
0)
0*
0+
0,
0B
b0 A
b100 E
11
#2060000
01
#2065000
b101 E
b1 A
11
#2070000
01
#2075000
1)
1*
1+
1,
1B
b0 A
b110 E
11
#2080000
01
#2085000
b111 E
b1 A
11
#2090000
01
#2095000
0)
0*
0+
0,
0B
b0 A
b1000 E
11
#2100000
01
#2105000
b1001 E
b1 A
11
#2110000
01
#2115000
1)
1*
1+
1,
1B
b0 A
b1010 E
11
#2120000
01
#2125000
b1011 E
b1 A
11
#2130000
01
#2135000
0)
0*
0+
0,
0B
b0 A
b1100 E
11
#2140000
01
#2145000
b1101 E
b1 A
11
#2150000
01
#2155000
1)
1*
1+
1,
1B
b0 A
b1110 E
11
#2160000
01
#2165000
b1111 E
b1 A
11
#2170000
01
#2175000
0)
0*
0+
0,
0B
b0 A
b10000 E
11
#2180000
01
#2185000
b10001 E
b1 A
11
#2190000
01
#2195000
1)
1*
1+
1,
1B
b0 A
b10010 E
11
#2200000
01
#2205000
b10011 E
b1 A
11
#2210000
01
#2215000
0)
0*
0+
0,
0B
b0 A
b10100 E
11
#2220000
01
#2225000
b10101 E
b1 A
11
#2230000
01
#2235000
1)
1*
1+
1,
1B
b0 A
b10110 E
11
#2240000
01
#2245000
b10111 E
b1 A
11
#2250000
01
#2255000
0)
0*
0+
0,
0B
b0 A
b11000 E
11
#2260000
01
#2265000
b11001 E
b1 A
11
#2270000
01
#2275000
1)
1*
1+
1,
1B
b0 A
b11010 E
11
#2280000
01
#2285000
b11011 E
b1 A
11
#2290000
01
#2295000
0)
0*
0+
0,
0B
b0 A
b11100 E
11
#2300000
01
#2305000
b11101 E
b1 A
11
#2310000
01
#2315000
1)
1*
1+
1,
1B
b0 A
b11110 E
11
#2320000
01
#2325000
b11111 E
b1 A
11
#2330000
01
#2335000
0)
0*
0+
0,
0B
b0 A
b100000 E
11
#2340000
01
#2345000
b100001 E
b1 A
11
#2350000
01
#2355000
1)
1*
1+
1,
1B
b0 A
b100010 E
11
#2360000
01
#2365000
b100011 E
b1 A
11
#2370000
01
#2375000
0)
0*
0+
0,
0B
b0 A
b100100 E
11
#2380000
01
#2385000
b100101 E
b1 A
11
#2390000
01
#2395000
1)
1*
1+
1,
1B
b0 A
b100110 E
11
#2400000
01
#2405000
1F
b1 D
b100111 E
b1 A
11
#2410000
01
#2415000
0/
1'
1(
00
0$
0F
0)
0*
0+
0,
0B
b0 A
b0 E
b1 C
11
#2420000
01
#2425000
b1 E
b1 A
11
#2430000
01
#2435000
1)
1*
1+
1,
1B
b0 A
b10 E
11
#2440000
01
#2445000
b11 E
b1 A
11
#2450000
01
#2455000
0)
0*
0+
0,
0B
b0 A
b100 E
11
#2460000
01
#2465000
b101 E
b1 A
11
#2470000
01
#2475000
1)
1*
1+
1,
1B
b0 A
b110 E
11
#2480000
01
#2485000
1F
b10 D
b111 E
b1 A
11
#2490000
01
#2495000
1#
0/
0'
10
0(
0F
0)
0*
0+
0,
0B
b0 A
b0 E
b10 C
11
#2500000
01
#2505000
b1 E
b1 A
11
#2510000
01
#2515000
1)
1*
1+
1,
1B
b0 A
b10 E
11
#2520000
01
#2525000
b11 E
b1 A
11
#2530000
01
#2535000
0)
0*
0+
0,
0B
b0 A
b100 E
11
#2540000
01
#2545000
b101 E
b1 A
11
#2550000
01
#2555000
1)
1*
1+
1,
1B
b0 A
b110 E
11
#2560000
01
#2565000
b111 E
b1 A
11
#2570000
01
#2575000
0)
0*
0+
0,
0B
b0 A
b1000 E
11
#2580000
01
#2585000
b1001 E
b1 A
11
#2590000
01
#2595000
1)
1*
1+
1,
1B
b0 A
b1010 E
11
#2600000
01
#2605000
b1011 E
b1 A
11
#2610000
01
#2615000
0)
0*
0+
0,
0B
b0 A
b1100 E
11
#2620000
01
#2625000
b1101 E
b1 A
11
#2630000
01
#2635000
1)
1*
1+
1,
1B
b0 A
b1110 E
11
#2640000
01
#2645000
b1111 E
b1 A
11
#2650000
01
#2655000
0)
0*
0+
0,
0B
b0 A
b10000 E
11
#2660000
01
#2665000
b10001 E
b1 A
11
#2670000
01
#2675000
1)
1*
1+
1,
1B
b0 A
b10010 E
11
#2680000
01
#2685000
b10011 E
b1 A
11
#2690000
01
#2695000
0)
0*
0+
0,
0B
b0 A
b10100 E
11
#2700000
01
#2705000
b10101 E
b1 A
11
#2710000
01
#2715000
1)
1*
1+
1,
1B
b0 A
b10110 E
11
#2720000
01
#2725000
b10111 E
b1 A
11
#2730000
01
#2735000
0)
0*
0+
0,
0B
b0 A
b11000 E
11
#2740000
01
#2745000
b11001 E
b1 A
11
#2750000
01
#2755000
1)
1*
1+
1,
1B
b0 A
b11010 E
11
#2760000
01
#2765000
b11011 E
b1 A
11
#2770000
01
#2775000
0)
0*
0+
0,
0B
b0 A
b11100 E
11
#2780000
01
#2785000
b11101 E
b1 A
11
#2790000
01
#2795000
1)
1*
1+
1,
1B
b0 A
b11110 E
11
#2800000
01
#2805000
b11111 E
b1 A
11
#2810000
01
#2815000
0)
0*
0+
0,
0B
b0 A
b100000 E
11
#2820000
01
#2825000
b100001 E
b1 A
11
#2830000
01
#2835000
1)
1*
1+
1,
1B
b0 A
b100010 E
11
#2840000
01
#2845000
b100011 E
b1 A
11
#2850000
01
#2855000
0)
0*
0+
0,
0B
b0 A
b100100 E
11
#2860000
01
#2865000
b100101 E
b1 A
11
#2870000
01
#2875000
1)
1*
1+
1,
1B
b0 A
b100110 E
11
#2880000
01
#2885000
1F
b11 D
b100111 E
b1 A
11
#2890000
01
#2895000
0.
1&
1'
0/
0#
0F
0)
0*
0+
0,
0B
b0 A
b0 E
b11 C
11
#2900000
01
#2905000
b1 E
b1 A
11
#2910000
01
#2915000
1)
1*
1+
1,
1B
b0 A
b10 E
11
#2920000
01
#2925000
b11 E
b1 A
11
#2930000
01
#2935000
0)
0*
0+
0,
0B
b0 A
b100 E
11
#2940000
01
#2945000
b101 E
b1 A
11
#2950000
01
#2955000
1)
1*
1+
1,
1B
b0 A
b110 E
11
#2960000
01
#2965000
1F
b100 D
b111 E
b1 A
11
#2970000
01
#2975000
1"
0.
0&
1/
0'
0F
0)
0*
0+
0,
0B
b0 A
b0 E
b100 C
11
#2980000
01
#2985000
b1 E
b1 A
11
#2990000
01
#2995000
1)
1*
1+
1,
1B
b0 A
b10 E
11
#3000000
01
#3005000
b11 E
b1 A
11
#3010000
01
#3015000
0)
0*
0+
0,
0B
b0 A
b100 E
11
#3020000
01
#3025000
b101 E
b1 A
11
#3030000
01
#3035000
1)
1*
1+
1,
1B
b0 A
b110 E
11
#3040000
01
#3045000
b111 E
b1 A
11
#3050000
01
#3055000
0)
0*
0+
0,
0B
b0 A
b1000 E
11
#3060000
01
#3065000
b1001 E
b1 A
11
#3070000
01
#3075000
1)
1*
1+
1,
1B
b0 A
b1010 E
11
#3080000
01
#3085000
b1011 E
b1 A
11
#3090000
01
